MANIFEST.in
README.md
requirements.txt
setup.py
callback/__init__.py
callback/admin.py
callback/apps.py
callback/forms.py
callback/models.py
callback/urls.py
callback/views.py
callback/locale/ru/LC_MESSAGES/django.mo
callback/locale/ru/LC_MESSAGES/django.po
callback/locale/uk/LC_MESSAGES/django.mo
callback/locale/uk/LC_MESSAGES/django.po
callback/migrations/0001_initial.py
callback/migrations/__init__.py
callback/templates/callback/email.html
callback/templates/callback/modal.html
django_mp_callback.egg-info/PKG-INFO
django_mp_callback.egg-info/SOURCES.txt
django_mp_callback.egg-info/dependency_links.txt
django_mp_callback.egg-info/top_level.txt