Metadata-Version: 2.1
Name: django-mp-callback
Version: 2.0.3
Summary: Django callback app
Home-page: https://github.com/pmaigutyak/mp-callback
Author: Paul Maigutyak
Author-email: pmaigutyak@gmail.com
License: MIT
Download-URL: https://github.com/pmaigutyak/mp-callback/archive/2.0.3.tar.gz
Platform: UNKNOWN
